{"6316c7c8-faec-46bf-89b2-229be843796c":{"id":"6316c7c8-faec-46bf-89b2-229be843796c","key":"12,28,G","tagsById":"{\"12\":{\"type\":\"withGenres\",\"id\":12,\"name\":\"Adventure\",\"lastActiveAt\":1745102660146},\"28\":{\"type\":\"withGenres\",\"id\":28,\"name\":\"Action\",\"lastActiveAt\":1745102660146},\"G\":{\"type\":\"certification\",\"id\":\"G\",\"certification\":\"G\",\"certificationCountry\":\"US\",\"lastActiveAt\":1745102660146}}","userId":"3076f8ff-9ba0-4514-b18c-220fe6950d76","createdAt":1745102663074}}